LICENSE
MANIFEST.in
README.md
VERSION
setup.py
lase/__init__.py
lase/git.py
lase/version.py
lase.egg-info/PKG-INFO
lase.egg-info/SOURCES.txt
lase.egg-info/dependency_links.txt
lase.egg-info/entry_points.txt
lase.egg-info/requires.txt
lase.egg-info/top_level.txt