Metadata-Version: 2.1
Name: lase
Version: 0.3.1
Summary: Gitflow release tool
Home-page: https://github.com/node13h/lase
Author: Sergej Alikov
Author-email: sergej.alikov@gmail.com
License: UNKNOWN
Platform: UNKNOWN
Classifier: Development Status :: 4 - Beta
Classifier: License :: OSI Approved :: MIT License
Classifier: Programming Language :: Python :: 3
